fds/__init__.py
fds/sdk/__init__.py
fds/sdk/GIPS/__init__.py
fds/sdk/GIPS/api_client.py
fds/sdk/GIPS/configuration.py
fds/sdk/GIPS/exceptions.py
fds/sdk/GIPS/model_utils.py
fds/sdk/GIPS/rest.py
fds/sdk/GIPS/api/__init__.py
fds/sdk/GIPS/api/gips_calculations_api.py
fds/sdk/GIPS/api/gips_lookups_api.py
fds/sdk/GIPS/apis/__init__.py
fds/sdk/GIPS/model/__init__.py
fds/sdk/GIPS/model/account_directories.py
fds/sdk/GIPS/model/account_directories_root.py
fds/sdk/GIPS/model/api_client_error_response.py
fds/sdk/GIPS/model/api_error.py
fds/sdk/GIPS/model/calculation_status.py
fds/sdk/GIPS/model/calculation_status_meta.py
fds/sdk/GIPS/model/calculation_status_root.py
fds/sdk/GIPS/model/calculation_unit_status.py
fds/sdk/GIPS/model/calculation_unit_status_meta.py
fds/sdk/GIPS/model/calculations_summary.py
fds/sdk/GIPS/model/calculations_summary_root.py
fds/sdk/GIPS/model/currency.py
fds/sdk/GIPS/model/currency_root.py
fds/sdk/GIPS/model/error.py
fds/sdk/GIPS/model/error_source.py
fds/sdk/GIPS/model/fact_set_protobuf_format_v1_date_time_format.py
fds/sdk/GIPS/model/fact_set_protobuf_format_v1_fds_format_settings.py
fds/sdk/GIPS/model/fact_set_protobuf_format_v1_number_format.py
fds/sdk/GIPS/model/fact_set_protobuf_format_v1_number_format_types_currency_standard_specifier.py
fds/sdk/GIPS/model/fact_set_protobuf_format_v1_number_format_types_digits.py
fds/sdk/GIPS/model/fact_set_protobuf_format_v1_number_format_types_exponential_standard_specifier.py
fds/sdk/GIPS/model/fact_set_protobuf_format_v1_number_format_types_numeric_standard_specifier.py
fds/sdk/GIPS/model/fact_set_protobuf_format_v1_number_format_types_percent_standard_specifier.py
fds/sdk/GIPS/model/fact_set_protobuf_format_v1_number_format_types_rounding.py
fds/sdk/GIPS/model/fact_set_protobuf_stach_v3_metadata_item.py
fds/sdk/GIPS/model/fact_set_protobuf_stach_v3_sort.py
fds/sdk/GIPS/model/fact_set_protobuf_stach_v3_sort_column.py
fds/sdk/GIPS/model/fact_set_protobuf_stach_v3_stach_v3_table.py
fds.sdk.GIPS-0.0.1.dist-info/LICENSE
fds.sdk.GIPS-0.0.1.dist-info/METADATA
fds.sdk.GIPS-0.0.1.dist-info/WHEEL
fds.sdk.GIPS-0.0.1.dist-info/top_level.txt
fds.sdk.GIPS-0.0.1.dist-info/RECORD
